problexity/ComplexityCalculator.py
problexity/__init__.py
problexity/_version.py
problexity/classification/__init__.py
problexity/classification/class_imbalance.py
problexity/classification/dimensionality.py
problexity/classification/feature_based.py
problexity/classification/gower.py
problexity/classification/linearity.py
problexity/classification/neighborhood.py
problexity/classification/network.py
problexity/regression/__init__.py
problexity/regression/correlation.py
problexity/regression/geometry.py
problexity/regression/linearity.py
problexity/regression/smoothness.py
problexity/tests/__init__.py
problexity/tests/test_classification.py
problexity/tests/test_regression.py
problexity-0.5.11.dist-info/LICENSE
problexity-0.5.11.dist-info/METADATA
problexity-0.5.11.dist-info/WHEEL
problexity-0.5.11.dist-info/top_level.txt
problexity-0.5.11.dist-info/RECORD
