Metadata-Version: 2.1
Name: problexity
Version: 0.5.11
Summary: The problexity module is an open-source python library containing the implementation of measures describing the complexity of the classification problem.
Home-page: https://w4k2.github.io/problexity/
Download-URL: https://github.com/w4k2/problexity
Maintainer: J. Komorniczak
Maintainer-email: joanna.komorniczak@vp.pl
License: GPL-3.0
Classifier: Development Status :: 4 - Beta
Classifier: Intended Audience :: Science/Research
Classifier: License :: OSI Approved :: GNU General Public License v3 (GPLv3)
Classifier: Programming Language :: Python
Classifier: Programming Language :: Python :: 3.7
Classifier: Topic :: Scientific/Engineering
Classifier: Topic :: Scientific/Engineering :: Artificial Intelligence
Classifier: Topic :: Software Development :: Libraries
Classifier: Topic :: Software Development :: Libraries :: Python Modules
License-File: LICENSE
Requires-Dist: numpy
Requires-Dist: scipy
Requires-Dist: scikit-learn
Requires-Dist: matplotlib
Requires-Dist: igraph
Requires-Dist: pandas
